gxdltk/__init__.py
gxdltk/config.py
gxdltk/data.py
gxdltk/eval.py
gxdltk/header.py
gxdltk/logger.py
gxdltk/nlp.py
gxdltk/t.py
gxdltk/trainer.py
gxdltk/ts.py
gxdltk/types.py
gxdltk/utils.py
gxdltk/data/__init__.py
gxdltk/data/corpus.py
gxdltk/data/header.py
gxdltk/mx/__init__.py
gxdltk/mx/data.py
gxdltk/mx/header.py
gxdltk/mx/nd.py
gxdltk/mx/train.py
gxdltk/th/__init__.py
gxdltk/th/data.py
gxdltk/th/header.py
gxdltk/th/hooker.py
gxdltk/th/tensor.py
gxdltk/th/utils.py
gxdltk-0.4a2.dist-info/LICENSE
gxdltk-0.4a2.dist-info/METADATA
gxdltk-0.4a2.dist-info/WHEEL
gxdltk-0.4a2.dist-info/top_level.txt
gxdltk-0.4a2.dist-info/RECORD
